agent_workstation/__init__.py
agent_workstation/version.py
agent_workstation-0.0.0.dist-info/LICENSE
agent_workstation-0.0.0.dist-info/METADATA
agent_workstation-0.0.0.dist-info/WHEEL
agent_workstation-0.0.0.dist-info/entry_points.txt
agent_workstation-0.0.0.dist-info/top_level.txt
agent_workstation-0.0.0.dist-info/RECORD
