Metadata-Version: 2.1
Name: agent-workstation
Version: 0.0.0
Summary: Agent-Workstation: An fully self-hosted multimodal agent framework for building local AI applications.
Home-page: https://github.com/wangxingjun778/agent-workstation
Author: wangxingjun778
Author-email: wangxingjun778@163.com
License: Apache License 2.0
Keywords: Agent,LLM,Multimodal,Self-Hosted
Classifier: Development Status :: 4 - Beta
Classifier: License :: OSI Approved :: Apache Software License
Classifier: Operating System :: OS Independent
Classifier: Programming Language :: Python :: 3
Classifier: Programming Language :: Python :: 3.9
Classifier: Programming Language :: Python :: 3.10
Classifier: Programming Language :: Python :: 3.11
Classifier: Programming Language :: Python :: 3.12
License-File: LICENSE
Requires-Dist: numpy
